setup.cfg
setup.py
dnaloop/__init__.py
dnaloop/cli.py
dnaloop/preprocess_chiapet_fastq.sh
dnaloop/preprocess_chiapet_set.sh
dnaloop/qc-report.R
dnaloop/qc-report.py
dnaloop/split_fastq.py
dnaloop.egg-info/PKG-INFO
dnaloop.egg-info/SOURCES.txt
dnaloop.egg-info/dependency_links.txt
dnaloop.egg-info/entry_points.txt
dnaloop.egg-info/not-zip-safe
dnaloop.egg-info/requires.txt
dnaloop.egg-info/top_level.txt
test/__init__.py
test/test_cli.py