Metadata-Version: 1.1
Name: dnaloop
Version: 0.5.16
Summary: A preprocessing and QC pipeline for ChIA-PET data.
Home-page: https://github.com/aryeelab/dnaloop
Author: Caleb Lareau and Martin Aryee
Author-email: aryee.martin@mgh.harvard.edu
License: BSD
Platform: any
Classifier: Development Status :: 3 - Alpha
Classifier: Environment :: Console
Classifier: Intended Audience :: Developers
Classifier: License :: OSI Approved :: BSD License
Classifier: Operating System :: POSIX
Classifier: Operating System :: MacOS
Classifier: Operating System :: Unix
Classifier: Programming Language :: Python
Classifier: Programming Language :: Python :: 2
Classifier: Topic :: Software Development :: Libraries :: Python Modules
